LICENSE
MANIFEST.in
README.md
setup.cfg
setup.py
version.py
limix_lmm/__init__.py
limix_lmm/_testit.py
limix_lmm/lmm.py
limix_lmm/lmm_core.py
limix_lmm/mtlmm.py
limix_lmm/mtlmm_helper.py
limix_lmm/util.py
limix_lmm.egg-info/PKG-INFO
limix_lmm.egg-info/SOURCES.txt
limix_lmm.egg-info/dependency_links.txt
limix_lmm.egg-info/requires.txt
limix_lmm.egg-info/top_level.txt
limix_lmm.egg-info/zip-safe
limix_lmm/plot/__init__.py
limix_lmm/plot/_qqplot.py
limix_lmm/plot/manhattan.py
limix_lmm/sh/__init__.py
limix_lmm/sh/download.py
limix_lmm/sh/unzip.py
limix_lmm/test/__init__.py
limix_lmm/test/test_mtmm_scan.py