Metadata-Version: 2.1
Name: limix-lmm
Version: 0.1.2
Summary: Linear mixed model for GWAS
Home-page: https://github.com/limix/limix-lmm
Author: Francesco Paolo Casale
Author-email: casale@ebi.ac.uk
Maintainer: Francesco Paolo Casale
Maintainer-email: casale@ebi.ac.uk
License: APACHE
Download-URL: https://github.com/limix/limix-lmm
Keywords: GWAS,LMM
Platform: Windows
Platform: MacOS
Platform: Linux
Classifier: Development Status :: 5 - Production/Stable
Classifier: License :: OSI Approved :: Apache Software License
Classifier: Operating System :: OS Independent
Classifier: Programming Language :: Python
